COPYING
MANIFEST.in
README.rst
fakeredis.py
setup.py
fakeredis_fix.egg-info/PKG-INFO
fakeredis_fix.egg-info/SOURCES.txt
fakeredis_fix.egg-info/dependency_links.txt
fakeredis_fix.egg-info/requires.txt
fakeredis_fix.egg-info/top_level.txt