Metadata-Version: 1.1
Name: fakeredis-fix
Version: 0.4.1
Summary: Fake implementation of redis API for testing purposes.
Home-page: https://github.com/jamesls/fakeredis
Author: James Saryerwinnie
Author-email: js@jamesls.com
License: BSD
Platform: UNKNOWN
Classifier: Development Status :: 5 - Production/Stable
Classifier: Programming Language :: Python :: 2.6
Classifier: Programming Language :: Python :: 2.7
Classifier: License :: OSI Approved :: BSD License
